[
  {
    "common": "Manzanita",
    "scientific": "Arctostaphylos spp.",
    "type": "shrub",
    "sun": "full sun",
    "soil": "well-drained",
    "water": "low",
    "flowerColor": "white to pink",
    "image": "https://inaturalist-open-data.s3.amazonaws.com/photos/709462/large.jpg",
    "image preview": {},
    "care ": "Evergreen shrub that thrives in dry, sunny conditions. Offers year-round structure.",
    "wildlife": "Bees, Pollinators",
    "form": "focal"
  },
  {
    "common": "California Fuchsia",
    "scientific": "Epilobium canum",
    "type": "perennial",
    "sun": "full sun",
    "soil": "well-drained",
    "water": "low",
    "flowerColor": "red",
    "image": "https://www.picturethisai.com/image-handle/website_cmsname/image/1080/515927637865594880.jpeg?x-oss-process=image/format,webp/resize,s_800&v=1.0",
    "image preview": {},
    "care ": "Spreads quickly and blooms late into summer, attracting hummingbirds.",
    "wildlife": "Hummingbirds",
    "form": "filler"
  },
  {
    "common": "Yarrow",
    "scientific": "Achillea millefolium",
    "type": "perennial",
    "sun": "full sun",
    "soil": "various",
    "water": "low",
    "flowerColor": "white",
    "image": "https://store.theodorepayne.org/cdn/shop/products/achmil-01.jpg?v=1688678954&width=751",
    "image preview": {},
    "care ": "Tough, drought-tolerant, and spreads readily. Great pollinator support.",
    "wildlife": "Bees, Butterflies",
    "form": "filler"
  },
  {
    "common": "Seaside Daisy",
    "scientific": "Erigeron glaucus",
    "type": "perennial",
    "sun": "full sun",
    "soil": "well-drained",
    "water": "low",
    "flowerColor": "lavender",
    "image": "https://calscape.org/storage/app/ExtData/allimages/Photos/Erigeron_glaucus_image65.jpg",
    "image preview": {},
    "care ": "Compact plant ideal for borders or erosion control on slopes.",
    "wildlife": "Bees, Butterflies",
    "form": "groundcover"
  },
  {
    "common": "Douglas Iris",
    "scientific": "Iris douglasiana",
    "type": "perennial",
    "sun": "part shade",
    "soil": "well-drained",
    "water": "moderate",
    "flowerColor": "purple",
    "image": "https://calscape.org/storage/app/ExtData/allimages/Photos/Iris_douglasiana_image7.jpg",
    "image preview": {},
    "care ": "Elegant woodland iris with showy flowers. Good for under trees.",
    "wildlife": "Pollinators",
    "form": "filler"
  },
  {
    "common": "California Poppy",
    "scientific": "Eschscholzia californica",
    "type": "perennial",
    "sun": "full sun",
    "soil": "sandy",
    "water": "low",
    "flowerColor": "orange",
    "image": "https://calscape.org/storage/app/species_images/calphotos/images/6666_6666_0317_0016.jpeg",
    "image preview": {},
    "care ": "Iconic CA native. Easy to grow and reseeds. Excellent for sunny borders.",
    "wildlife": "Bees, Butterflies",
    "form": "filler"
  },
  {
    "common": "Cleveland Sage",
    "scientific": "Salvia clevelandii",
    "type": "shrub",
    "sun": "full sun",
    "soil": "well-drained",
    "water": "very low",
    "flowerColor": "purple-blue",
    "image": "https://calscape.org/storage/app/ExtData/allimages/Photos/Salvia_clevelandii_image_56.jpg",
    "image preview": {},
    "care ": "Highly aromatic. Excellent for fragrance gardens and dry hillsides.",
    "wildlife": "Hummingbirds, Bees",
    "form": "focal"
  },
  {
    "common": "Blue-Eyed Grass",
    "scientific": "Sisyrinchium bellum",
    "type": "perennial",
    "sun": "full sun",
    "soil": "well-drained",
    "water": "low",
    "flowerColor": "blue",
    "image": "https://calscape.org/storage/app/ExtData/allimages/Photos/Sisyrinchium_bellum_image_39.jpg",
    "image preview": {},
    "care ": "Looks like grass, blooms like a wildflower. Great near borders.",
    "wildlife": "Bees, Pollinators",
    "form": "filler"
  },
  {
    "common": "Toyon",
    "scientific": "Heteromeles arbutifolia",
    "type": "shrub",
    "sun": "full sun",
    "soil": "well-drained",
    "water": "low",
    "flowerColor": "white",
    "image": "https://store.theodorepayne.org/cdn/shop/files/Toyon_MarieAstridGonzales-2.jpg?v=1732663406&width=814",
    "image preview": {},
    "care ": "Large evergreen shrub with bright red berries in winter.",
    "wildlife": "Birds",
    "form": "focal"
  },
  {
    "common": "Monkeyflower",
    "scientific": "Diplacus spp.",
    "type": "perennial",
    "sun": "full sun",
    "soil": "well-drained",
    "water": "low",
    "flowerColor": "orange, red, yellow",
    "image": "https://calscape.org/storage/app/species_images/calphotos/images/0000_0000_0717_0521.jpeg",
    "image preview": {},
    "care ": "Cheerful flowers and great drought tolerance make this a favorite.",
    "wildlife": "Hummingbirds",
    "form": "filler"
  },
  {
    "common": "",
    "scientific": "",
    "type": "",
    "sun": "",
    "soil": "",
    "water": "",
    "flowerColor": "",
    "image": "",
    "image preview": {},
    "care ": "",
    "wildlife": "",
    "form": ""
  },
  {
    "common": "",
    "scientific": "",
    "type": "",
    "sun": "",
    "soil": "",
    "water": "",
    "flowerColor": "",
    "image": "",
    "image preview": {},
    "care ": "",
    "wildlife": "",
    "form": ""
  },
  {
    "common": "",
    "scientific": "",
    "type": "",
    "sun": "",
    "soil": "",
    "water": "",
    "flowerColor": "",
    "image": "",
    "image preview": {},
    "care ": "",
    "wildlife": "",
    "form": ""
  },
  {
    "common": "",
    "scientific": "",
    "type": "",
    "sun": "",
    "soil": "",
    "water": "",
    "flowerColor": "",
    "image": "",
    "image preview": {},
    "care ": "",
    "wildlife": "",
    "form": ""
  },
  {
    "common": "",
    "scientific": "",
    "type": "",
    "sun": "",
    "soil": "",
    "water": "",
    "flowerColor": "",
    "image": "",
    "image preview": {},
    "care ": "",
    "wildlife": "",
    "form": ""
  },
  {
    "common": "",
    "scientific": "",
    "type": "",
    "sun": "",
    "soil": "",
    "water": "",
    "flowerColor": "",
    "image": "",
    "image preview": {},
    "care ": "",
    "wildlife": "",
    "form": ""
  },
  {
    "common": "",
    "scientific": "",
    "type": "",
    "sun": "",
    "soil": "",
    "water": "",
    "flowerColor": "",
    "image": "",
    "image preview": {},
    "care ": "",
    "wildlife": "",
    "form": ""
  },
  {
    "common": "",
    "scientific": "",
    "type": "",
    "sun": "",
    "soil": "",
    "water": "",
    "flowerColor": "",
    "image": "",
    "image preview": {},
    "care ": "",
    "wildlife": "",
    "form": ""
  },
  {
    "common": "",
    "scientific": "",
    "type": "",
    "sun": "",
    "soil": "",
    "water": "",
    "flowerColor": "",
    "image": "",
    "image preview": {},
    "care ": "",
    "wildlife": "",
    "form": ""
  },
  {
    "common": "",
    "scientific": "",
    "type": "",
    "sun": "",
    "soil": "",
    "water": "",
    "flowerColor": "",
    "image": "",
    "image preview": {},
    "care ": "",
    "wildlife": "",
    "form": ""
  },
  {
    "common": "",
    "scientific": "",
    "type": "",
    "sun": "",
    "soil": "",
    "water": "",
    "flowerColor": "",
    "image": "",
    "image preview": {},
    "care ": "",
    "wildlife": "",
    "form": ""
  },
  {
    "common": "",
    "scientific": "",
    "type": "",
    "sun": "",
    "soil": "",
    "water": "",
    "flowerColor": "",
    "image": "",
    "image preview": {},
    "care ": "",
    "wildlife": "",
    "form": ""
  },
  {
    "common": "",
    "scientific": "",
    "type": "",
    "sun": "",
    "soil": "",
    "water": "",
    "flowerColor": "",
    "image": "",
    "image preview": {},
    "care ": "",
    "wildlife": "",
    "form": ""
  },
  {
    "common": "",
    "scientific": "",
    "type": "",
    "sun": "",
    "soil": "",
    "water": "",
    "flowerColor": "",
    "image": "",
    "image preview": {},
    "care ": "",
    "wildlife": "",
    "form": ""
  },
  {
    "common": "",
    "scientific": "",
    "type": "",
    "sun": "",
    "soil": "",
    "water": "",
    "flowerColor": "",
    "image": "",
    "image preview": {},
    "care ": "",
    "wildlife": "",
    "form": ""
  },
  {
    "common": "",
    "scientific": "",
    "type": "",
    "sun": "",
    "soil": "",
    "water": "",
    "flowerColor": "",
    "image": "",
    "image preview": {},
    "care ": "",
    "wildlife": "",
    "form": ""
  },
  {
    "common": "",
    "scientific": "",
    "type": "",
    "sun": "",
    "soil": "",
    "water": "",
    "flowerColor": "",
    "image": "",
    "image preview": {},
    "care ": "",
    "wildlife": "",
    "form": ""
  },
  {
    "common": "",
    "scientific": "",
    "type": "",
    "sun": "",
    "soil": "",
    "water": "",
    "flowerColor": "",
    "image": "",
    "image preview": {},
    "care ": "",
    "wildlife": "",
    "form": ""
  },
  {
    "common": "",
    "scientific": "",
    "type": "",
    "sun": "",
    "soil": "",
    "water": "",
    "flowerColor": "",
    "image": "",
    "image preview": {},
    "care ": "",
    "wildlife": "",
    "form": ""
  },
  {
    "common": "",
    "scientific": "",
    "type": "",
    "sun": "",
    "soil": "",
    "water": "",
    "flowerColor": "",
    "image": "",
    "image preview": {},
    "care ": "",
    "wildlife": "",
    "form": ""
  },
  {
    "common": "",
    "scientific": "",
    "type": "",
    "sun": "",
    "soil": "",
    "water": "",
    "flowerColor": "",
    "image": "",
    "image preview": {},
    "care ": "",
    "wildlife": "",
    "form": ""
  },
  {
    "common": "",
    "scientific": "",
    "type": "",
    "sun": "",
    "soil": "",
    "water": "",
    "flowerColor": "",
    "image": "",
    "image preview": {},
    "care ": "",
    "wildlife": "",
    "form": ""
  },
  {
    "common": "",
    "scientific": "",
    "type": "",
    "sun": "",
    "soil": "",
    "water": "",
    "flowerColor": "",
    "image": "",
    "image preview": {},
    "care ": "",
    "wildlife": "",
    "form": ""
  },
  {
    "common": "",
    "scientific": "",
    "type": "",
    "sun": "",
    "soil": "",
    "water": "",
    "flowerColor": "",
    "image": "",
    "image preview": {},
    "care ": "",
    "wildlife": "",
    "form": ""
  },
  {
    "common": "",
    "scientific": "",
    "type": "",
    "sun": "",
    "soil": "",
    "water": "",
    "flowerColor": "",
    "image": "",
    "image preview": {},
    "care ": "",
    "wildlife": "",
    "form": ""
  },
  {
    "common": "",
    "scientific": "",
    "type": "",
    "sun": "",
    "soil": "",
    "water": "",
    "flowerColor": "",
    "image": "",
    "image preview": {},
    "care ": "",
    "wildlife": "",
    "form": ""
  },
  {
    "common": "",
    "scientific": "",
    "type": "",
    "sun": "",
    "soil": "",
    "water": "",
    "flowerColor": "",
    "image": "",
    "image preview": {},
    "care ": "",
    "wildlife": "",
    "form": ""
  },
  {
    "common": "",
    "scientific": "",
    "type": "",
    "sun": "",
    "soil": "",
    "water": "",
    "flowerColor": "",
    "image": "",
    "image preview": {},
    "care ": "",
    "wildlife": "",
    "form": ""
  },
  {
    "common": "",
    "scientific": "",
    "type": "",
    "sun": "",
    "soil": "",
    "water": "",
    "flowerColor": "",
    "image": "",
    "image preview": {},
    "care ": "",
    "wildlife": "",
    "form": ""
  },
  {
    "common": "",
    "scientific": "",
    "type": "",
    "sun": "",
    "soil": "",
    "water": "",
    "flowerColor": "",
    "image": "",
    "image preview": {},
    "care ": "",
    "wildlife": "",
    "form": ""
  },
  {
    "common": "",
    "scientific": "",
    "type": "",
    "sun": "",
    "soil": "",
    "water": "",
    "flowerColor": "",
    "image": "",
    "image preview": {},
    "care ": "",
    "wildlife": "",
    "form": ""
  },
  {
    "common": "",
    "scientific": "",
    "type": "",
    "sun": "",
    "soil": "",
    "water": "",
    "flowerColor": "",
    "image": "",
    "image preview": {},
    "care ": "",
    "wildlife": "",
    "form": ""
  },
  {
    "common": "",
    "scientific": "",
    "type": "",
    "sun": "",
    "soil": "",
    "water": "",
    "flowerColor": "",
    "image": "",
    "image preview": {},
    "care ": "",
    "wildlife": "",
    "form": ""
  },
  {
    "common": "",
    "scientific": "",
    "type": "",
    "sun": "",
    "soil": "",
    "water": "",
    "flowerColor": "",
    "image": "",
    "image preview": {},
    "care ": "",
    "wildlife": "",
    "form": ""
  },
  {
    "common": "",
    "scientific": "",
    "type": "",
    "sun": "",
    "soil": "",
    "water": "",
    "flowerColor": "",
    "image": "",
    "image preview": {},
    "care ": "",
    "wildlife": "",
    "form": ""
  },
  {
    "common": "",
    "scientific": "",
    "type": "",
    "sun": "",
    "soil": "",
    "water": "",
    "flowerColor": "",
    "image": "",
    "image preview": {},
    "care ": "",
    "wildlife": "",
    "form": ""
  },
  {
    "common": "",
    "scientific": "",
    "type": "",
    "sun": "",
    "soil": "",
    "water": "",
    "flowerColor": "",
    "image": "",
    "image preview": {},
    "care ": "",
    "wildlife": "",
    "form": ""
  },
  {
    "common": "",
    "scientific": "",
    "type": "",
    "sun": "",
    "soil": "",
    "water": "",
    "flowerColor": "",
    "image": "",
    "image preview": {},
    "care ": "",
    "wildlife": "",
    "form": ""
  },
  {
    "common": "",
    "scientific": "",
    "type": "",
    "sun": "",
    "soil": "",
    "water": "",
    "flowerColor": "",
    "image": "",
    "image preview": {},
    "care ": "",
    "wildlife": "",
    "form": ""
  },
  {
    "common": "",
    "scientific": "",
    "type": "",
    "sun": "",
    "soil": "",
    "water": "",
    "flowerColor": "",
    "image": "",
    "image preview": {},
    "care ": "",
    "wildlife": "",
    "form": ""
  },
  {
    "common": "",
    "scientific": "",
    "type": "",
    "sun": "",
    "soil": "",
    "water": "",
    "flowerColor": "",
    "image": "",
    "image preview": {},
    "care ": "",
    "wildlife": "",
    "form": ""
  },
  {
    "common": "",
    "scientific": "",
    "type": "",
    "sun": "",
    "soil": "",
    "water": "",
    "flowerColor": "",
    "image": "",
    "image preview": {},
    "care ": "",
    "wildlife": "",
    "form": ""
  },
  {
    "common": "",
    "scientific": "",
    "type": "",
    "sun": "",
    "soil": "",
    "water": "",
    "flowerColor": "",
    "image": "",
    "image preview": {},
    "care ": "",
    "wildlife": "",
    "form": ""
  },
  {
    "common": "",
    "scientific": "",
    "type": "",
    "sun": "",
    "soil": "",
    "water": "",
    "flowerColor": "",
    "image": "",
    "image preview": {},
    "care ": "",
    "wildlife": "",
    "form": ""
  },
  {
    "common": "",
    "scientific": "",
    "type": "",
    "sun": "",
    "soil": "",
    "water": "",
    "flowerColor": "",
    "image": "",
    "image preview": {},
    "care ": "",
    "wildlife": "",
    "form": ""
  },
  {
    "common": "",
    "scientific": "",
    "type": "",
    "sun": "",
    "soil": "",
    "water": "",
    "flowerColor": "",
    "image": "",
    "image preview": {},
    "care ": "",
    "wildlife": "",
    "form": ""
  },
  {
    "common": "",
    "scientific": "",
    "type": "",
    "sun": "",
    "soil": "",
    "water": "",
    "flowerColor": "",
    "image": "",
    "image preview": {},
    "care ": "",
    "wildlife": "",
    "form": ""
  },
  {
    "common": "",
    "scientific": "",
    "type": "",
    "sun": "",
    "soil": "",
    "water": "",
    "flowerColor": "",
    "image": "",
    "image preview": {},
    "care ": "",
    "wildlife": "",
    "form": ""
  },
  {
    "common": "",
    "scientific": "",
    "type": "",
    "sun": "",
    "soil": "",
    "water": "",
    "flowerColor": "",
    "image": "",
    "image preview": {},
    "care ": "",
    "wildlife": "",
    "form": ""
  },
  {
    "common": "",
    "scientific": "",
    "type": "",
    "sun": "",
    "soil": "",
    "water": "",
    "flowerColor": "",
    "image": "",
    "image preview": {},
    "care ": "",
    "wildlife": "",
    "form": ""
  },
  {
    "common": "",
    "scientific": "",
    "type": "",
    "sun": "",
    "soil": "",
    "water": "",
    "flowerColor": "",
    "image": "",
    "image preview": {},
    "care ": "",
    "wildlife": "",
    "form": ""
  },
  {
    "common": "",
    "scientific": "",
    "type": "",
    "sun": "",
    "soil": "",
    "water": "",
    "flowerColor": "",
    "image": "",
    "image preview": {},
    "care ": "",
    "wildlife": "",
    "form": ""
  },
  {
    "common": "",
    "scientific": "",
    "type": "",
    "sun": "",
    "soil": "",
    "water": "",
    "flowerColor": "",
    "image": "",
    "image preview": {},
    "care ": "",
    "wildlife": "",
    "form": ""
  },
  {
    "common": "",
    "scientific": "",
    "type": "",
    "sun": "",
    "soil": "",
    "water": "",
    "flowerColor": "",
    "image": "",
    "image preview": {},
    "care ": "",
    "wildlife": "",
    "form": ""
  },
  {
    "common": "",
    "scientific": "",
    "type": "",
    "sun": "",
    "soil": "",
    "water": "",
    "flowerColor": "",
    "image": "",
    "image preview": {},
    "care ": "",
    "wildlife": "",
    "form": ""
  },
  {
    "common": "",
    "scientific": "",
    "type": "",
    "sun": "",
    "soil": "",
    "water": "",
    "flowerColor": "",
    "image": "",
    "image preview": {},
    "care ": "",
    "wildlife": "",
    "form": ""
  },
  {
    "common": "",
    "scientific": "",
    "type": "",
    "sun": "",
    "soil": "",
    "water": "",
    "flowerColor": "",
    "image": "",
    "image preview": {},
    "care ": "",
    "wildlife": "",
    "form": ""
  },
  {
    "common": "",
    "scientific": "",
    "type": "",
    "sun": "",
    "soil": "",
    "water": "",
    "flowerColor": "",
    "image": "",
    "image preview": {},
    "care ": "",
    "wildlife": "",
    "form": ""
  },
  {
    "common": "",
    "scientific": "",
    "type": "",
    "sun": "",
    "soil": "",
    "water": "",
    "flowerColor": "",
    "image": "",
    "image preview": {},
    "care ": "",
    "wildlife": "",
    "form": ""
  },
  {
    "common": "",
    "scientific": "",
    "type": "",
    "sun": "",
    "soil": "",
    "water": "",
    "flowerColor": "",
    "image": "",
    "image preview": {},
    "care ": "",
    "wildlife": "",
    "form": ""
  },
  {
    "common": "",
    "scientific": "",
    "type": "",
    "sun": "",
    "soil": "",
    "water": "",
    "flowerColor": "",
    "image": "",
    "image preview": {},
    "care ": "",
    "wildlife": "",
    "form": ""
  },
  {
    "common": "",
    "scientific": "",
    "type": "",
    "sun": "",
    "soil": "",
    "water": "",
    "flowerColor": "",
    "image": "",
    "image preview": {},
    "care ": "",
    "wildlife": "",
    "form": ""
  },
  {
    "common": "",
    "scientific": "",
    "type": "",
    "sun": "",
    "soil": "",
    "water": "",
    "flowerColor": "",
    "image": "",
    "image preview": {},
    "care ": "",
    "wildlife": "",
    "form": ""
  },
  {
    "common": "",
    "scientific": "",
    "type": "",
    "sun": "",
    "soil": "",
    "water": "",
    "flowerColor": "",
    "image": "",
    "image preview": {},
    "care ": "",
    "wildlife": "",
    "form": ""
  },
  {
    "common": "",
    "scientific": "",
    "type": "",
    "sun": "",
    "soil": "",
    "water": "",
    "flowerColor": "",
    "image": "",
    "image preview": {},
    "care ": "",
    "wildlife": "",
    "form": ""
  },
  {
    "common": "",
    "scientific": "",
    "type": "",
    "sun": "",
    "soil": "",
    "water": "",
    "flowerColor": "",
    "image": "",
    "image preview": {},
    "care ": "",
    "wildlife": "",
    "form": ""
  },
  {
    "common": "",
    "scientific": "",
    "type": "",
    "sun": "",
    "soil": "",
    "water": "",
    "flowerColor": "",
    "image": "",
    "image preview": {},
    "care ": "",
    "wildlife": "",
    "form": ""
  },
  {
    "common": "",
    "scientific": "",
    "type": "",
    "sun": "",
    "soil": "",
    "water": "",
    "flowerColor": "",
    "image": "",
    "image preview": {},
    "care ": "",
    "wildlife": "",
    "form": ""
  },
  {
    "common": "",
    "scientific": "",
    "type": "",
    "sun": "",
    "soil": "",
    "water": "",
    "flowerColor": "",
    "image": "",
    "image preview": {},
    "care ": "",
    "wildlife": "",
    "form": ""
  },
  {
    "common": "",
    "scientific": "",
    "type": "",
    "sun": "",
    "soil": "",
    "water": "",
    "flowerColor": "",
    "image": "",
    "image preview": {},
    "care ": "",
    "wildlife": "",
    "form": ""
  },
  {
    "common": "",
    "scientific": "",
    "type": "",
    "sun": "",
    "soil": "",
    "water": "",
    "flowerColor": "",
    "image": "",
    "image preview": {},
    "care ": "",
    "wildlife": "",
    "form": ""
  },
  {
    "common": "",
    "scientific": "",
    "type": "",
    "sun": "",
    "soil": "",
    "water": "",
    "flowerColor": "",
    "image": "",
    "image preview": {},
    "care ": "",
    "wildlife": "",
    "form": ""
  },
  {
    "common": "",
    "scientific": "",
    "type": "",
    "sun": "",
    "soil": "",
    "water": "",
    "flowerColor": "",
    "image": "",
    "image preview": {},
    "care ": "",
    "wildlife": "",
    "form": ""
  },
  {
    "common": "",
    "scientific": "",
    "type": "",
    "sun": "",
    "soil": "",
    "water": "",
    "flowerColor": "",
    "image": "",
    "image preview": {},
    "care ": "",
    "wildlife": "",
    "form": ""
  },
  {
    "common": "",
    "scientific": "",
    "type": "",
    "sun": "",
    "soil": "",
    "water": "",
    "flowerColor": "",
    "image": "",
    "image preview": {},
    "care ": "",
    "wildlife": "",
    "form": ""
  },
  {
    "common": "",
    "scientific": "",
    "type": "",
    "sun": "",
    "soil": "",
    "water": "",
    "flowerColor": "",
    "image": "",
    "image preview": {},
    "care ": "",
    "wildlife": "",
    "form": ""
  },
  {
    "common": "",
    "scientific": "",
    "type": "",
    "sun": "",
    "soil": "",
    "water": "",
    "flowerColor": "",
    "image": "",
    "image preview": {},
    "care ": "",
    "wildlife": "",
    "form": ""
  },
  {
    "common": "",
    "scientific": "",
    "type": "",
    "sun": "",
    "soil": "",
    "water": "",
    "flowerColor": "",
    "image": "",
    "image preview": {},
    "care ": "",
    "wildlife": "",
    "form": ""
  },
  {
    "common": "",
    "scientific": "",
    "type": "",
    "sun": "",
    "soil": "",
    "water": "",
    "flowerColor": "",
    "image": "",
    "image preview": {},
    "care ": "",
    "wildlife": "",
    "form": ""
  },
  {
    "common": "",
    "scientific": "",
    "type": "",
    "sun": "",
    "soil": "",
    "water": "",
    "flowerColor": "",
    "image": "",
    "image preview": {},
    "care ": "",
    "wildlife": "",
    "form": ""
  },
  {
    "common": "",
    "scientific": "",
    "type": "",
    "sun": "",
    "soil": "",
    "water": "",
    "flowerColor": "",
    "image": "",
    "image preview": {},
    "care ": "",
    "wildlife": "",
    "form": ""
  },
  {
    "common": "",
    "scientific": "",
    "type": "",
    "sun": "",
    "soil": "",
    "water": "",
    "flowerColor": "",
    "image": "",
    "image preview": {},
    "care ": "",
    "wildlife": "",
    "form": ""
  },
  {
    "common": "",
    "scientific": "",
    "type": "",
    "sun": "",
    "soil": "",
    "water": "",
    "flowerColor": "",
    "image": "",
    "image preview": {},
    "care ": "",
    "wildlife": "",
    "form": ""
  },
  {
    "common": "",
    "scientific": "",
    "type": "",
    "sun": "",
    "soil": "",
    "water": "",
    "flowerColor": "",
    "image": "",
    "image preview": {},
    "care ": "",
    "wildlife": "",
    "form": ""
  },
  {
    "common": "",
    "scientific": "",
    "type": "",
    "sun": "",
    "soil": "",
    "water": "",
    "flowerColor": "",
    "image": "",
    "image preview": {},
    "care ": "",
    "wildlife": "",
    "form": ""
  },
  {
    "common": "",
    "scientific": "",
    "type": "",
    "sun": "",
    "soil": "",
    "water": "",
    "flowerColor": "",
    "image": "",
    "image preview": {},
    "care ": "",
    "wildlife": "",
    "form": ""
  },
  {
    "common": "",
    "scientific": "",
    "type": "",
    "sun": "",
    "soil": "",
    "water": "",
    "flowerColor": "",
    "image": "",
    "image preview": {},
    "care ": "",
    "wildlife": "",
    "form": ""
  },
  {
    "common": "",
    "scientific": "",
    "type": "",
    "sun": "",
    "soil": "",
    "water": "",
    "flowerColor": "",
    "image": "",
    "image preview": {},
    "care ": "",
    "wildlife": "",
    "form": ""
  },
  {
    "common": "",
    "scientific": "",
    "type": "",
    "sun": "",
    "soil": "",
    "water": "",
    "flowerColor": "",
    "image": "",
    "image preview": {},
    "care ": "",
    "wildlife": "",
    "form": ""
  }
]